ecoscape_utilities/__init__.py
ecoscape_utilities/bird_runs.py
ecoscape_utilities/ebird_db.py
ecoscape_utilities-0.0.45.dist-info/licenses/LICENSE.md
ecoscape_utilities-0.0.45.dist-info/METADATA
ecoscape_utilities-0.0.45.dist-info/WHEEL
ecoscape_utilities-0.0.45.dist-info/top_level.txt
ecoscape_utilities-0.0.45.dist-info/RECORD
