Metadata-Version: 2.4
Name: ecoscape-utilities
Version: 0.0.45
Summary: A collection of EcoScape utilities.
Author-email: Luca de Alfaro <luca@ucsc.edu>, Coen Adler <ctadler@ucsc.edu>, Artie Nazarov <anazarov@ucsc.edu>, Natalia Ocampo-Peñuela <nocampop@ucsc.edu>, Jasmine Tai <cjtai@ucsc.edu>, Natalie Valett <nvalett@ucsc.edu>
Project-URL: Homepage, https://github.com/ecoscape-earth/ecoscape-utilities
Project-URL: Bug Tracker, https://github.com/ecoscape-earth/ecoscape-utilities/issues
Classifier: Programming Language :: Python :: 3
Classifier: License :: OSI Approved :: BSD License
Classifier: Operating System :: OS Independent
Requires-Python: >=3.7
License-File: LICENSE.md
Requires-Dist: pandas>=1.0.0
Requires-Dist: scgt>=0.0.20
Requires-Dist: pyproj>=3.0.0
Requires-Dist: numpy>=1.0.0
Dynamic: license-file
